MANIFEST.in
README.md
VERSION
licence.html
setup.py
dposlib/__init__.py
dposlib/cfg.py
dposlib/net.py
dposlib/rest.py
dposlib.egg-info/PKG-INFO
dposlib.egg-info/SOURCES.txt
dposlib.egg-info/dependency_links.txt
dposlib.egg-info/requires.txt
dposlib.egg-info/top_level.txt
dposlib/ark/__init__.py
dposlib/ark/api.py
dposlib/ark/crypto.py
dposlib/ark/ldgr.py
dposlib/ark/mixin.py
dposlib/ark/slots.py
dposlib/ark/tx.py
dposlib/ark/builders/__init__.py
dposlib/ark/builders/v2.py
dposlib/ark/builders/v3.py
dposlib/ark/cold/__init__.py
dposlib/ark/cold/ark.py
dposlib/ark/cold/dark.py
dposlib/ark/cold/dnos.py
dposlib/ark/cold/nos.py
dposlib/ark/cold/sxp.py
dposlib/ark/cold/tsxp.py
dposlib/ark/serde/__init__.py
dposlib/ark/serde/v2.py
dposlib/ark/serde/v3.py
dposlib/util/__init__.py
dposlib/util/asynch.py
dposlib/util/bin.py
dposlib/util/data.py
test/fixtures-serials.json
test/fixtures.json
test/test_ark_aip11.py
test/test_ark_api.py
test/test_ark_crypto.py