Metadata-Version: 2.1
Name: dposlib
Version: 1.0.0
Summary: light api compatible with ARK blockchain and forks
Home-page: https://github.com/Moustikitos/dpos
Author: Toons
Author-email: moustikitos@gmail.com
Maintainer: Toons
Maintainer-email: moustikitos@gmail.com
License: Copyright 2018, MIT licence
Download-URL: https://github.com/Moustikitos/dpos/archive/master.zip
Keywords: api,ark,blockchain
Platform: UNKNOWN
Classifier: Development Status :: 5 - Production/Stable
Classifier: Environment :: Console
Classifier: Environment :: Web Environment
Classifier: Intended Audience :: Developers
Classifier: Intended Audience :: End Users/Desktop
Classifier: License :: OSI Approved :: MIT License
Classifier: Operating System :: OS Independent
Classifier: Programming Language :: Python
Classifier: Programming Language :: Python :: 3
License-File: licence.html
